ask_weather/__init__.py
ask_weather/agent.py
ask_weather/tools.py
ask_weather/utils/__init__.py
ask_weather/utils/file_utils.py
ask_weather/utils/logger.py
ask_weather-0.1.5.dist-info/METADATA
ask_weather-0.1.5.dist-info/WHEEL
ask_weather-0.1.5.dist-info/RECORD
