Metadata-Version: 2.1
Name: ask-weather
Version: 0.1.5
Summary: "A weather query agent using LangChain and OpenWeatherMap API"
License: MIT
Author: doyikim
Author-email: doyikim34@naver.com
Requires-Python: >=3.9,<4.0
Classifier: License :: OSI Approved :: MIT License
Classifier: Programming Language :: Python :: 3
Classifier: Programming Language :: Python :: 3.9
Classifier: Programming Language :: Python :: 3.10
Classifier: Programming Language :: Python :: 3.11
Classifier: Programming Language :: Python :: 3.12
Requires-Dist: langchain (>=0.3.3,<0.4.0)
Requires-Dist: langchain-openai (>=0.2.2,<0.3.0)
Requires-Dist: python-dotenv (>=1.0.1,<2.0.0)
Requires-Dist: pyyaml (>=6.0.2,<7.0.0)
Requires-Dist: requests (>=2.32.3,<3.0.0)
Requires-Dist: setuptools (>=75.1.0,<76.0.0)
Requires-Dist: torch (==2.2.0)
